metapost/__init__.py
metapost/metapost.py
metapost/metapost_reader.py
metapost-1.0.3.dist-info/LICENSE.md
metapost-1.0.3.dist-info/METADATA
metapost-1.0.3.dist-info/WHEEL
metapost-1.0.3.dist-info/top_level.txt
metapost-1.0.3.dist-info/RECORD
