Metadata-Version: 2.1
Name: metapost
Version: 1.0.3
Summary: Tools for interpreting MetaPost
Home-page: https://github.com/thitta/Python-MetaPost
Author: Hsufeng Lee
Author-email: thittalee@gmail.com
License: MIT License
Platform: UNKNOWN
Classifier: Programming Language :: Python :: 3
Classifier: Operating System :: OS Independent
Requires-Dist: datetime
Requires-Dist: markdown
Requires-Dist: typing
Requires-Dist: tzlocal
